postat/__init__.py
postat/classes/__init__.py
postat/classes/api.py
postat/classes/config.py
postat/classes/http.py
postat/classes/log.py
postat/classes/parser.py
postat-0.9.0.dist-info/METADATA
postat-0.9.0.dist-info/WHEEL
postat-0.9.0.dist-info/licenses/LICENSE
postat-0.9.0.dist-info/RECORD
