Metadata-Version: 2.1
Name: postat
Version: 0.9.0
Summary: Simple Python wrapper to fetch data from Austrian Post (post.at)
Project-URL: Homepage, https://kumig.it/kumitterer/postat
Project-URL: Bug Tracker, https://kumig.it/kumitterer/postat/issues
Author-email: Kumi Mitterer <postat@kumi.email>
License: Copyright (c) 2023 Kumi Mitterer <postat@kumi.email>
License-File: LICENSE
Classifier: License :: OSI Approved :: MIT License
Classifier: Operating System :: OS Independent
Classifier: Programming Language :: Python :: 3
Requires-Python: >=3.10
